pytt_sign/__init__.py
pytt_sign/sign.py
pytt_sign-1.0.2.dist-info/METADATA
pytt_sign-1.0.2.dist-info/WHEEL
pytt_sign-1.0.2.dist-info/top_level.txt
pytt_sign-1.0.2.dist-info/RECORD
